antares_results/__init__.py
antares_results/version.py
antares_results/HHH/__init__.py
antares_results/HHH/momenta.py
antares_results/HHH/target_values.py
antares_results/HHH/test_coefficients.py
antares_results/HHH/ggHHH/__init__.py
antares_results/HHH/ggHHH/pm/__init__.py
antares_results/HHH/ggHHH/pp/__init__.py
antares_results/Vjj/__init__.py
antares_results/Vjj/momenta.py
antares_results/Vjj/target_values.py
antares_results/Vjj/test_remainders.py
antares_results/Vjj/qQQqll/__init__.py
antares_results/Vjj/qQQqll/nmhv/__init__.py
antares_results/Vjj/qggqll/__init__.py
antares_results/Vjj/qggqll/mhv/__init__.py
antares_results/Vjj/qggqll/nmhv/__init__.py
antares_results/jjj/__init__.py
antares_results/jjj/ggggg/__init__.py
antares_results/jjj/ggggg/all_plus/__init__.py
antares_results/jjj/ggggg/mhv/__init__.py
antares_results/jjj/ggggg/single_minus/__init__.py
antares_results/jjj/uubddbg/__init__.py
antares_results/jjj/uubddbg/mhv/__init__.py
antares_results/jjj/uubggg/__init__.py
antares_results/jjj/uubggg/mhv/__init__.py
antares_results/jjj/uubggg/single_minus/__init__.py
antares_results/jjjj/__init__.py
antares_results/jjjj/momenta.py
antares_results/jjjj/target_values.py
antares_results/jjjj/test_coefficients.py
antares_results/ttH/__init__.py
antares_results/ttH/momenta.py
antares_results/ttH/target_values.py
antares_results/ttH/test_coefficients.py
antares_results/ttH/qqttH/__init__.py
antares_results/ttH/qqttH/pm/__init__.py
antares_results-0.0.4.dist-info/LICENSE.txt
antares_results-0.0.4.dist-info/METADATA
antares_results-0.0.4.dist-info/WHEEL
antares_results-0.0.4.dist-info/top_level.txt
antares_results-0.0.4.dist-info/RECORD
