Metadata-Version: 2.1
Name: antares-results
Version: 0.0.4
Summary: Spinor Helicity Amplitudes
Home-page: https://github.com/GDeLaurentis/antares-results
Download-URL: https://github.com/GDeLaurentis/antares-results/archive/v0.0.4.tar.gz
Author: Giuseppe De Laurentis
Author-email: g.dl@hotmail.it
License: GNU General Public License v3.0
Project-URL: Documentation, https://gdelaurentis.github.io/antares-results/
Project-URL: Issues, https://github.com/GDeLaurentis/antares-results/issues
Keywords: Spinor Helicity,Scattering Amplitudes
Classifier: Development Status :: 4 - Beta
Classifier: Intended Audience :: Science/Research
Classifier: Topic :: Scientific/Engineering :: Physics
Classifier: License :: OSI Approved :: GNU General Public License v3 (GPLv3)
Classifier: Programming Language :: Python :: 3.9
Classifier: Programming Language :: Python :: 3.10
Classifier: Programming Language :: Python :: 3.11
Classifier: Programming Language :: Python :: 3.12
License-File: LICENSE.txt
Requires-Dist: lips
Requires-Dist: recommonmark
Requires-Dist: termcolor
